src/__init__.py
src/app.py
src/dita_processor.py
src/file_utils.py
tests/__init__.py
tests/test_app.py
tests/test_dita_processor.py
tests/test_file_utils.py
dita_parser-1.0.2.dist-info/METADATA
dita_parser-1.0.2.dist-info/WHEEL
dita_parser-1.0.2.dist-info/entry_points.txt
dita_parser-1.0.2.dist-info/top_level.txt
dita_parser-1.0.2.dist-info/RECORD
