Metadata-Version: 2.1
Name: dita_parser
Version: 1.0.2
Summary: DITA File Merger and Splitter Utility
Author: Frederic Everaert
Author-email: frederic.everaert@crosslang.com
